jayden_opensearch_retriever-0.1.1.dist-info/licenses/LICENSE
opensearch_retriever/__init__.py
opensearch_retriever/retriever.py
jayden_opensearch_retriever-0.1.1.dist-info/METADATA
jayden_opensearch_retriever-0.1.1.dist-info/WHEEL
jayden_opensearch_retriever-0.1.1.dist-info/top_level.txt
jayden_opensearch_retriever-0.1.1.dist-info/RECORD
