Metadata-Version: 2.4
Name: jayden-opensearch-retriever
Version: 0.1.1
Summary: OpenSearch 기반 검색 및 검색 결과 검색 도구
Author-email: Jayden <jayden.kim@nxtcloud.kr>
Maintainer-email: Jayden <jayden.kim@nxtcloud.kr>
Project-URL: Homepage, https://github.com/yourusername/opensearch-retriever
Project-URL: Repository, https://github.com/yourusername/opensearch-retriever
Project-URL: Documentation, https://opensearch-retriever.readthedocs.io/
Project-URL: Bug Tracker, https://github.com/yourusername/opensearch-retriever/issues
Keywords: opensearch,search,retriever,elasticsearch
Classifier: Development Status :: 3 - Alpha
Classifier: Intended Audience :: Developers
Classifier: License :: OSI Approved :: MIT License
Classifier: Programming Language :: Python :: 3
Classifier: Programming Language :: Python :: 3.8
Classifier: Programming Language :: Python :: 3.9
Classifier: Programming Language :: Python :: 3.10
Classifier: Programming Language :: Python :: 3.11
Classifier: Topic :: Software Development :: Libraries :: Python Modules
Classifier: Topic :: Internet :: WWW/HTTP :: Indexing/Search
Requires-Python: >=3.8
License-File: LICENSE
Requires-Dist: requests>=2.25.0
Requires-Dist: opensearch-py>=2.0.0
Provides-Extra: dev
Requires-Dist: pytest>=7.0.0; extra == "dev"
Dynamic: license-file
